django_seq/__init__.py
django_seq/__version__.py
django_seq/_typing.py
django_seq/_typing_ext.py
django_seq/admin.py
django_seq/apps.py
django_seq/connector.py
django_seq/fields.py
django_seq/globals.py
django_seq/models.py
django_seq/py.typed
django_seq/registry.py
django_seq/segmentation.py
django_seq/setup.py
django_seq/tests.py
django_seq/utils.py
django_seq/conf/__init__.py
django_seq/conf/settings.py
django_seq/migrations/0001_initial.py
django_seq/migrations/__init__.py
django_seq-1.0.0a5.dist-info/LICENSE
django_seq-1.0.0a5.dist-info/METADATA
django_seq-1.0.0a5.dist-info/WHEEL
django_seq-1.0.0a5.dist-info/top_level.txt
django_seq-1.0.0a5.dist-info/zip-safe
django_seq-1.0.0a5.dist-info/RECORD
