Metadata-Version: 2.1
Name: django-seq
Version: 1.0.0a5
Summary: Django implementation of gapless sequences, with a configurable field type.
Home-page: https://github.com/ertgl/django-seq/
Author: Ertuğrul Noyan Keremoğlu
Author-email: ertugkeremoglu@gmail.com
License: MIT
Classifier: Framework :: Django
Classifier: Intended Audience :: Developers
Classifier: License :: OSI Approved :: MIT License
Classifier: Natural Language :: English
Classifier: Operating System :: OS Independent
Classifier: Programming Language :: Python :: 3
Classifier: Topic :: Software Development :: Libraries :: Python Modules
Classifier: Topic :: Utilities
Classifier: Typing :: Typed
License-File: LICENSE
Requires-Dist: django
